[{"ID":"fpy2zxtlKMS3uzP97PLnUQ==","支部名":"上海市复旦大学中国语言文学系2018级本科生第一团支部","支部类型":"06BYBTZB","组织人数":26,"团委名":"上海市复旦大学中国语言文学系团委"},{"ID":"4iXtkb3kuy7fIIL7T47_wA==","支部名":"上海市复旦大学中国语言文学系2018级本科生第二团支部","支部类型":"06BYBTZB","组织人数":25,"团委名":"上海市复旦大学中国语言文学系团委"},{"ID":"bZncQzcKCLWYkF0bJxNcVA==","支部名":"上海市复旦大学中国语言文学系2018级本科生第三团支部","支部类型":"06BYBTZB","组织人数":27,"团委名":"上海市复旦大学中国语言文学系团委"},{"ID":"1MHVfwSfZzKyE37WrSJMoQ==","支部名":"上海市复旦大学中国语言文学系2018级本科生第四团支部","支部类型":"06BYBTZB","组织人数":26,"团委名":"上海市复旦大学中国语言文学系团委"},{"ID":"OIhGN9GqzoJ3e4AhFbdNew==","支部名":"上海市复旦大学中国语言文学系2018级本科生第五团支部","支部类型":"06BYBTZB","组织人数":24,"团委名":"上海市复旦大学中国语言文学系团委"},{"ID":"FDMJq07jeeoFKPBElNDcvw==","支部名":"上海市复旦大学中国语言文学系2018级科硕研究生第三团支部","支部类型":"06BYBTZB","组织人数":2,"团委名":"上海市复旦大学中国语言文学系团委"},{"ID":"W98fP8eE9Eisx3cUf0hBfQ==","支部名":"上海市复旦大学中国语言文学系2018级出版团支部","支部类型":"06BYBTZB","组织人数":1,"团委名":"上海市复旦大学中国语言文学系团委"},{"ID":"LCcC-1pLHJYue9iBO3gCWw==","支部名":"上海市复旦大学中国语言文学系2019级本科生第一团支部","支部类型":"01TZB","组织人数":26,"团委名":"上海市复旦大学中国语言文学系团委"},{"ID":"DujN_3icZ4yd4acOoIdnIg==","支部名":"上海市复旦大学中国语言文学系2019级本科生第二团支部","支部类型":"01TZB","组织人数":27,"团委名":"上海市复旦大学中国语言文学系团委"},{"ID":"eFLkhA5mDaw7SMSAOMWmTA==","支部名":"上海市复旦大学中国语言文学系2019级本科生第三团支部","支部类型":"01TZB","组织人数":28,"团委名":"上海市复旦大学中国语言文学系团委"},{"ID":"tmC6yCczcD__B89P60D6BQ==","支部名":"上海市复旦大学中国语言文学系2019级本科生第四团支部","支部类型":"01TZB","组织人数":29,"团委名":"上海市复旦大学中国语言文学系团委"},{"ID":"juNcDpdhG7K4aEwIEd1twQ==","支部名":"上海市复旦大学中国语言文学系2019级博士生团支部","支部类型":"06BYBTZB","组织人数":8,"团委名":"上海市复旦大学中国语言文学系团委"},{"ID":"yAxD3L8qQNyBoYchan4hYw==","支部名":"上海市复旦大学中国语言文学系2019级科硕研究生第一团支部","支部类型":"06BYBTZB","组织人数":19,"团委名":"上海市复旦大学中国语言文学系团委"},{"ID":"dv35bkxAe71nFbZMHhmjXA==","支部名":"上海市复旦大学中国语言文学系2019级科硕研究生第二团支部","支部类型":"06BYBTZB","组织人数":20,"团委名":"上海市复旦大学中国语言文学系团委"},{"ID":"4nKMZdRTiEaglPQxOa6iJg==","支部名":"上海市复旦大学中国语言文学系2019级科硕研究生第三团支部","支部类型":"06BYBTZB","组织人数":21,"团委名":"上海市复旦大学中国语言文学系团委"},{"ID":"8bXu65CSWN2OV8_XqWYc3A==","支部名":"上海市复旦大学中国语言文学系2019级mfa团支部","支部类型":"06BYBTZB","组织人数":15,"团委名":"上海市复旦大学中国语言文学系团委"},{"ID":"Hqvb04KhuaPSnAF6PVmo5g==","支部名":"上海市复旦大学中国语言文学系2020级MFA团支部","支部类型":"01TZB","组织人数":16,"团委名":"上海市复旦大学中国语言文学系团委"},{"ID":"x9gJsYMwxiX6-STSb0vCNg==","支部名":"上海市复旦大学中国语言文学系2020级出版团支部","支部类型":"06BYBTZB","组织人数":22,"团委名":"上海市复旦大学中国语言文学系团委"},{"ID":"VSbhPeKY0jaL1lnvjKVYAw==","支部名":"上海市复旦大学中国语言文学系2020级科硕第一团支部","支部类型":"01TZB","组织人数":20,"团委名":"上海市复旦大学中国语言文学系团委"},{"ID":"VyqJYtnmQ4VIAOuWyYuj4w==","支部名":"上海市复旦大学中国语言文学系2020级科硕第二团支部","支部类型":"01TZB","组织人数":33,"团委名":"上海市复旦大学中国语言文学系团委"},{"ID":"cd7k3iUrs8BwOUpPH8NdGg==","支部名":"上海市复旦大学中国语言文学系2020级科硕第三团支部","支部类型":"06BYBTZB","组织人数":25,"团委名":"上海市复旦大学中国语言文学系团委"},{"ID":"Qjl-XHuS-79U7D-M6qrYvA==","支部名":"上海市复旦大学中国语言文学系2020级本科生第一团支部","支部类型":"01TZB","组织人数":25,"团委名":"上海市复旦大学中国语言文学系团委"},{"ID":"KPBGbPP28RZorJkjbwel0Q==","支部名":"上海市复旦大学中国语言文学系2020级本科生第二团支部","支部类型":"01TZB","组织人数":24,"团委名":"上海市复旦大学中国语言文学系团委"},{"ID":"B1TWBOrfPBiULk74pJFaJw==","支部名":"上海市复旦大学中国语言文学系2020级本科生第三团支部","支部类型":"01TZB","组织人数":24,"团委名":"上海市复旦大学中国语言文学系团委"},{"ID":"46a2jsuRMl46_IPFxs-YEA==","支部名":"上海市复旦大学中国语言文学系2020级本科生第四团支部","支部类型":"01TZB","组织人数":24,"团委名":"上海市复旦大学中国语言文学系团委"},{"ID":"8lA-Qe6VQhTAQJdoog-u1A==","支部名":"上海市复旦大学中国语言文学系2020级博士第一团支部","支部类型":"01TZB","组织人数":26,"团委名":"上海市复旦大学中国语言文学系团委"},{"ID":"u0VEXx1KK8Y9tXYlFgOZyw==","支部名":"上海市复旦大学中国语言文学系2021级MFA团支部","支部类型":"01TZB","组织人数":17,"团委名":"上海市复旦大学中国语言文学系团委"},{"ID":"-P1TexTUOzIvC1iK72tFYQ==","支部名":"上海市复旦大学中国语言文学系2021级出版团支部","支部类型":"01TZB","组织人数":19,"团委名":"上海市复旦大学中国语言文学系团委"},{"ID":"sJ-XCTLoyHmGZ0FvBJlTzQ==","支部名":"上海市复旦大学中国语言文学系2021级博士生团支部","支部类型":"01TZB","组织人数":29,"团委名":"上海市复旦大学中国语言文学系团委"},{"ID":"TFn053CL05URFX1_Z7-x4g==","支部名":"上海市复旦大学中国语言文学系2021级本科生第一团支部","支部类型":"01TZB","组织人数":21,"团委名":"上海市复旦大学中国语言文学系团委"},{"ID":"Gb3HUV3mEHY3eAcw9FjpAg==","支部名":"上海市复旦大学中国语言文学系2021级本科生第二团支部","支部类型":"01TZB","组织人数":21,"团委名":"上海市复旦大学中国语言文学系团委"},{"ID":"a1kXoMDiRMv8eC0aMiG5wA==","支部名":"上海市复旦大学中国语言文学系2021级本科生第三团支部","支部类型":"01TZB","组织人数":21,"团委名":"上海市复旦大学中国语言文学系团委"},{"ID":"0bxU89GN2TZrA8a8dCrbBA==","支部名":"上海市复旦大学中国语言文学系2021级本科生第四团支部","支部类型":"01TZB","组织人数":18,"团委名":"上海市复旦大学中国语言文学系团委"},{"ID":"V3oZ09akAEpHdU3aPgeKLg==","支部名":"上海市复旦大学中国语言文学系2021级科硕第一团支部","支部类型":"01TZB","组织人数":26,"团委名":"上海市复旦大学中国语言文学系团委"},{"ID":"7QAXjpediz4_BWV8KdhjMQ==","支部名":"上海市复旦大学中国语言文学系2021级科硕第二团支部","支部类型":"01TZB","组织人数":23,"团委名":"上海市复旦大学中国语言文学系团委"},{"ID":"930nYSwHg50AdILgN9ywIQ==","支部名":"上海市复旦大学中国语言文学系2021级科硕第三团支部","支部类型":"01TZB","组织人数":27,"团委名":"上海市复旦大学中国语言文学系团委"},{"ID":"kDduieoF2TodT6GPCaKNkg==","支部名":"上海市复旦大学中国语言文学系2021级本科生第五团支部","支部类型":"01TZB","组织人数":22,"团委名":"上海市复旦大学中国语言文学系团委"},{"ID":"cKiGNJojDdag3FAE-Qqo0Q==","支部名":"上海市复旦大学中国语言文学系2021级本科生第六团支部","支部类型":"01TZB","组织人数":21,"团委名":"上海市复旦大学中国语言文学系团委"},{"ID":"lw_EGtEZj8zsvBCjkUz0SA==","支部名":"上海市复旦大学中国语言文学系流动团支部","支部类型":"06BYBTZB","组织人数":214,"团委名":"上海市复旦大学中国语言文学系团委"},{"ID":"0vMOa0ppyAUBqmwcDfO6GA==","支部名":"上海市复旦大学外国语言文学学院2018级本科生第三团支部","支部类型":"06BYBTZB","组织人数":26,"团委名":"上海市复旦大学外国语言文学学院团委"},{"ID":"egMj13oB5BEj7kW70VmECQ==","支部名":"上海市复旦大学外国语言文学学院2018级本科生第五团支部","支部类型":"06BYBTZB","组织人数":29,"团委名":"上海市复旦大学外国语言文学学院团委"},{"ID":"oIj-thUEVPK9pq4lfubeew==","支部名":"上海市复旦大学外国语言文学学院博士研究生团支部","支部类型":"01TZB","组织人数":6,"团委名":"上海市复旦大学外国语言文学学院团委"},{"ID":"M0uorVLBeJ81_63QcI7F0g==","支部名":"上海市复旦大学外国语言文学学院2017级本科生团总支","支部类型":"02TZZ","组织人数":3,"团委名":"上海市复旦大学外国语言文学学院团委"},{"ID":"yY09l0GTZJgPn13SUEpoug==","支部名":"上海市复旦大学外国语言文学学院2019级科学硕士研究生团支部","支部类型":"06BYBTZB","组织人数":33,"团委名":"上海市复旦大学外国语言文学学院团委"},{"ID":"IlsbfpfeRe5Y81WFZV-g7w==","支部名":"上海市复旦大学外国语言文学学院2018级本科生第一团支部","支部类型":"06BYBTZB","组织人数":27,"团总支名":"上海市复旦大学外国语言文学学院2018级本科生团总支","团委名":"上海市复旦大学外国语言文学学院团委"},{"ID":"XIiBIZmofXJ23WSKE4TSzQ==","支部名":"上海市复旦大学外国语言文学学院2018级本科生第二团支部","支部类型":"06BYBTZB","组织人数":26,"团总支名":"上海市复旦大学外国语言文学学院2018级本科生团总支","团委名":"上海市复旦大学外国语言文学学院团委"},{"ID":"zMyyI3UBjBFKSdgsBa-kJw==","支部名":"上海市复旦大学外国语言文学学院2018级本科生第四团支部","支部类型":"06BYBTZB","组织人数":33,"团总支名":"上海市复旦大学外国语言文学学院2018级本科生团总支","团委名":"上海市复旦大学外国语言文学学院团委"},{"ID":"tSKH-JmcSKnYWmvs5HRZBA==","支部名":"上海市复旦大学外国语言文学学院2019级本科生2019级本科生第一团支部","支部类型":"01TZB","组织人数":21,"团总支名":"上海市复旦大学外国语言文学学院2019级本科生团总支","团委名":"上海市复旦大学外国语言文学学院团委"},{"ID":"f5SNQT2LHlwgKPVQb6k6UA==","支部名":"上海市复旦大学外国语言文学学院2019级本科生2019级本科生英翻西班第二团支部","支部类型":"01TZB","组织人数":24,"团总支名":"上海市复旦大学外国语言文学学院2019级本科生团总支","团委名":"上海市复旦大学外国语言文学学院团委"},{"ID":"iuwC7gfGXABSLAAnAbF2zw==","支部名":"上海市复旦大学外国语言文学学院2019级本科生2019级本科生第三团支部","支部类型":"01TZB","组织人数":30,"团总支名":"上海市复旦大学外国语言文学学院2019级本科生团总支","团委名":"上海市复旦大学外国语言文学学院团委"},{"ID":"8JV5y0vU5hzrfTJWS8vCsQ==","支部名":"上海市复旦大学外国语言文学学院2019级本科生第四团支部","支部类型":"01TZB","组织人数":22,"团总支名":"上海市复旦大学外国语言文学学院2019级本科生团总支","团委名":"上海市复旦大学外国语言文学学院团委"},{"ID":"Xr3CVZFU6u1YFp-5aItbJA==","支部名":"上海市复旦大学外国语言文学学院2019级本科生第五团支部","支部类型":"01TZB","组织人数":26,"团总支名":"上海市复旦大学外国语言文学学院2019级本科生团总支","团委名":"上海市复旦大学外国语言文学学院团委"},{"ID":"TNp1p8_QolWpf1IZe3CWUA==","支部名":"上海市复旦大学外国语言文学学院2019级本科生2019级本科生第六团支部","支部类型":"01TZB","组织人数":24,"团总支名":"上海市复旦大学外国语言文学学院2019级本科生团总支","团委名":"上海市复旦大学外国语言文学学院团委"},{"ID":"6Ydb-PNpGk20nMbWDZat6Q==","支部名":"上海市复旦大学外国语言文学学院2020级科学硕士研究生团支部","支部类型":"01TZB","组织人数":38,"团委名":"上海市复旦大学外国语言文学学院团委"},{"ID":"k9B2sA3NLo29BgI_OIpUxw==","支部名":"上海市复旦大学外国语言文学学院2020级翻译硕士研究生团支部","支部类型":"06BYBTZB","组织人数":32,"团委名":"上海市复旦大学外国语言文学学院团委"},{"ID":"sp3pL9CmBZdgmJfKxUpe1w==","支部名":"上海市复旦大学外国语言文学学院2020级本科生第一团支部","支部类型":"01TZB","组织人数":28,"团委名":"上海市复旦大学外国语言文学学院团委"}]